trellogy/__init__.py
trellogy/attachment.py
trellogy/board.py
trellogy/card.py
trellogy/component.py
trellogy/error.py
trellogy/label.py
trellogy/list.py
trellogy/trash_bin.py
trellogy-2.0.3.dist-info/METADATA
trellogy-2.0.3.dist-info/WHEEL
trellogy-2.0.3.dist-info/top_level.txt
trellogy-2.0.3.dist-info/RECORD
