Metadata-Version: 2.1
Name: trellogy
Version: 2.0.3
Summary: Trello board managing tool via Trello REST API
Home-page: https://github.com/chiantiscarlett/trellogy
Author: Chianti Scarlett
Author-email: chianti.scarlett@gmail.com
License: UNKNOWN
Platform: UNKNOWN
Classifier: Programming Language :: Python :: 3
Classifier: License :: OSI Approved :: MIT License
Classifier: Operating System :: OS Independent
Requires-Dist: requests
